[
  {
    "__type__": "cc.SpriteFrame",
    "content": {
      "name": "game_minigame_totalscore_iconshare",
      "texture": "67B4U0gL1NZ5uxmGRkV5ZW",
      "rect": [
        1,
        1,
        29,
        28
      ],
      "offset": [
        0,
        0
      ],
      "originalSize": [
        31,
        30
      ],
      "capInsets": [
        0,
        0,
        0,
        0
      ]
    }
  },
  {
    "__type__": "cc.SpriteFrame",
    "content": {
      "name": "font",
      "texture": "c3PXyl6wREUaeFN7Rb0YNG",
      "rect": [
        2,
        2,
        904,
        508
      ],
      "offset": [
        0,
        0
      ],
      "originalSize": [
        908,
        512
      ],
      "capInsets": [
        0,
        0,
        0,
        0
      ]
    }
  },
  {
    "__type__": "cc.BitmapFont",
    "_name": "font",
    "spriteFrame": {
      "__uuid__": "9bV14S70RAzbHdlagTTLg+"
    },
    "fontSize": 90,
    "_fntConfig": {
      "commonHeight": 108,
      "fontSize": 90,
      "atlasName": "font.png",
      "fontDefDictionary": {
        "32": {
          "rect": {
            "x": 0,
            "y": 0,
            "width": 0,
            "height": 0
          },
          "xOffset": 0,
          "yOffset": 72,
          "xAdvance": 21
        },
        "33": {
          "rect": {
            "x": 592,
            "y": 167,
            "width": 30,
            "height": 84
          },
          "xOffset": -1,
          "yOffset": 3,
          "xAdvance": 25
        },
        "34": {
          "rect": {
            "x": 443,
            "y": 188,
            "width": 38,
            "height": 38
          },
          "xOffset": -2,
          "yOffset": 1,
          "xAdvance": 30
        },
        "35": {
          "rect": {
            "x": 662,
            "y": 99,
            "width": 71,
            "height": 71
          },
          "xOffset": -1,
          "yOffset": 16,
          "xAdvance": 65
        },
        "36": {
          "rect": {
            "x": 687,
            "y": 2,
            "width": 53,
            "height": 91
          },
          "xOffset": -1,
          "yOffset": 5,
          "xAdvance": 47
        },
        "37": {
          "rect": {
            "x": 579,
            "y": 2,
            "width": 75,
            "height": 80
          },
          "xOffset": -2,
          "yOffset": 7,
          "xAdvance": 67
        },
        "38": {
          "rect": {
            "x": 672,
            "y": 172,
            "width": 76,
            "height": 82
          },
          "xOffset": -1,
          "yOffset": 6,
          "xAdvance": 69
        },
        "39": {
          "rect": {
            "x": 314,
            "y": 251,
            "width": 24,
            "height": 38
          },
          "xOffset": -2,
          "yOffset": 1,
          "xAdvance": 16
        },
        "40": {
          "rect": {
            "x": 624,
            "y": 84,
            "width": 36,
            "height": 99
          },
          "xOffset": -1,
          "yOffset": 6,
          "xAdvance": 29
        },
        "41": {
          "rect": {
            "x": 619,
            "y": 339,
            "width": 36,
            "height": 99
          },
          "xOffset": -2,
          "yOffset": 6,
          "xAdvance": 29
        },
        "42": {
          "rect": {
            "x": 490,
            "y": 354,
            "width": 56,
            "height": 61
          },
          "xOffset": -2,
          "yOffset": 2,
          "xAdvance": 48
        },
        "43": {
          "rect": {
            "x": 214,
            "y": 452,
            "width": 47,
            "height": 48
          },
          "xOffset": -1,
          "yOffset": 27,
          "xAdvance": 40
        },
        "44": {
          "rect": {
            "x": 272,
            "y": 84,
            "width": 32,
            "height": 38
          },
          "xOffset": -6,
          "yOffset": 59,
          "xAdvance": 21
        },
        "45": {
          "rect": {
            "x": 157,
            "y": 483,
            "width": 47,
            "height": 23
          },
          "xOffset": 2,
          "yOffset": 41,
          "xAdvance": 45
        },
        "46": {
          "rect": {
            "x": 312,
            "y": 482,
            "width": 26,
            "height": 28
          },
          "xOffset": -1,
          "yOffset": 59,
          "xAdvance": 21
        },
        "47": {
          "rect": {
            "x": 636,
            "y": 185,
            "width": 34,
            "height": 94
          },
          "xOffset": -2,
          "yOffset": 7,
          "xAdvance": 25
        },
        "48": {
          "rect": {
            "x": 809,
            "y": 241,
            "width": 58,
            "height": 72
          },
          "xOffset": 0,
          "yOffset": 15,
          "xAdvance": 54
        },
        "49": {
          "rect": {
            "x": 735,
            "y": 97,
            "width": 47,
            "height": 71
          },
          "xOffset": -1,
          "yOffset": 16,
          "xAdvance": 41
        },
        "50": {
          "rect": {
            "x": 779,
            "y": 2,
            "width": 57,
            "height": 71
          },
          "xOffset": -2,
          "yOffset": 15,
          "xAdvance": 49
        },
        "51": {
          "rect": {
            "x": 750,
            "y": 170,
            "width": 52,
            "height": 82
          },
          "xOffset": -1,
          "yOffset": 15,
          "xAdvance": 48
        },
        "52": {
          "rect": {
            "x": 784,
            "y": 75,
            "width": 61,
            "height": 80
          },
          "xOffset": -3,
          "yOffset": 16,
          "xAdvance": 51
        },
        "53": {
          "rect": {
            "x": 754,
            "y": 254,
            "width": 53,
            "height": 82
          },
          "xOffset": -1,
          "yOffset": 15,
          "xAdvance": 47
        },
        "54": {
          "rect": {
            "x": 804,
            "y": 157,
            "width": 58,
            "height": 82
          },
          "xOffset": 1,
          "yOffset": 6,
          "xAdvance": 54
        },
        "55": {
          "rect": {
            "x": 847,
            "y": 2,
            "width": 59,
            "height": 81
          },
          "xOffset": -3,
          "yOffset": 16,
          "xAdvance": 48
        },
        "56": {
          "rect": {
            "x": 779,
            "y": 338,
            "width": 56,
            "height": 82
          },
          "xOffset": 1,
          "yOffset": 6,
          "xAdvance": 53
        },
        "57": {
          "rect": {
            "x": 779,
            "y": 422,
            "width": 57,
            "height": 82
          },
          "xOffset": -1,
          "yOffset": 15,
          "xAdvance": 54
        },
        "58": {
          "rect": {
            "x": 258,
            "y": 298,
            "width": 26,
            "height": 64
          },
          "xOffset": 1,
          "yOffset": 24,
          "xAdvance": 24
        },
        "59": {
          "rect": {
            "x": 555,
            "y": 437,
            "width": 32,
            "height": 73
          },
          "xOffset": -4,
          "yOffset": 24,
          "xAdvance": 25
        },
        "61": {
          "rect": {
            "x": 263,
            "y": 464,
            "width": 47,
            "height": 37
          },
          "xOffset": 2,
          "yOffset": 33,
          "xAdvance": 47
        },
        "63": {
          "rect": {
            "x": 592,
            "y": 253,
            "width": 42,
            "height": 84
          },
          "xOffset": 0,
          "yOffset": 3,
          "xAdvance": 35
        },
        "64": {
          "rect": {
            "x": 657,
            "y": 281,
            "width": 95,
            "height": 101
          },
          "xOffset": -1,
          "yOffset": 6,
          "xAdvance": 88
        },
        "65": {
          "rect": {
            "x": 214,
            "y": 370,
            "width": 71,
            "height": 80
          },
          "xOffset": -4,
          "yOffset": 7,
          "xAdvance": 58
        },
        "66": {
          "rect": {
            "x": 244,
            "y": 132,
            "width": 60,
            "height": 80
          },
          "xOffset": 3,
          "yOffset": 7,
          "xAdvance": 58
        },
        "67": {
          "rect": {
            "x": 244,
            "y": 214,
            "width": 68,
            "height": 82
          },
          "xOffset": 0,
          "yOffset": 6,
          "xAdvance": 63
        },
        "68": {
          "rect": {
            "x": 297,
            "y": 2,
            "width": 72,
            "height": 80
          },
          "xOffset": 3,
          "yOffset": 7,
          "xAdvance": 71
        },
        "69": {
          "rect": {
            "x": 306,
            "y": 84,
            "width": 55,
            "height": 81
          },
          "xOffset": 3,
          "yOffset": 6,
          "xAdvance": 52
        },
        "70": {
          "rect": {
            "x": 287,
            "y": 298,
            "width": 51,
            "height": 81
          },
          "xOffset": 3,
          "yOffset": 6,
          "xAdvance": 46
        },
        "71": {
          "rect": {
            "x": 314,
            "y": 167,
            "width": 70,
            "height": 82
          },
          "xOffset": 0,
          "yOffset": 6,
          "xAdvance": 66
        },
        "72": {
          "rect": {
            "x": 363,
            "y": 84,
            "width": 69,
            "height": 81
          },
          "xOffset": 3,
          "yOffset": 6,
          "xAdvance": 72
        },
        "73": {
          "rect": {
            "x": 287,
            "y": 381,
            "width": 27,
            "height": 81
          },
          "xOffset": 3,
          "yOffset": 6,
          "xAdvance": 29
        },
        "74": {
          "rect": {
            "x": 316,
            "y": 381,
            "width": 34,
            "height": 99
          },
          "xOffset": -3,
          "yOffset": 6,
          "xAdvance": 29
        },
        "75": {
          "rect": {
            "x": 340,
            "y": 251,
            "width": 65,
            "height": 81
          },
          "xOffset": 3,
          "yOffset": 6,
          "xAdvance": 59
        },
        "76": {
          "rect": {
            "x": 386,
            "y": 167,
            "width": 55,
            "height": 81
          },
          "xOffset": 3,
          "yOffset": 6,
          "xAdvance": 50
        },
        "77": {
          "rect": {
            "x": 434,
            "y": 2,
            "width": 77,
            "height": 81
          },
          "xOffset": 3,
          "yOffset": 6,
          "xAdvance": 79
        },
        "78": {
          "rect": {
            "x": 352,
            "y": 334,
            "width": 67,
            "height": 81
          },
          "xOffset": 3,
          "yOffset": 6,
          "xAdvance": 69
        },
        "79": {
          "rect": {
            "x": 407,
            "y": 250,
            "width": 78,
            "height": 82
          },
          "xOffset": 0,
          "yOffset": 6,
          "xAdvance": 74
        },
        "80": {
          "rect": {
            "x": 371,
            "y": 2,
            "width": 57,
            "height": 80
          },
          "xOffset": 3,
          "yOffset": 7,
          "xAdvance": 53
        },
        "81": {
          "rect": {
            "x": 443,
            "y": 85,
            "width": 87,
            "height": 101
          },
          "xOffset": 0,
          "yOffset": 6,
          "xAdvance": 74
        },
        "82": {
          "rect": {
            "x": 513,
            "y": 2,
            "width": 64,
            "height": 80
          },
          "xOffset": 3,
          "yOffset": 7,
          "xAdvance": 59
        },
        "83": {
          "rect": {
            "x": 352,
            "y": 417,
            "width": 58,
            "height": 82
          },
          "xOffset": 0,
          "yOffset": 6,
          "xAdvance": 53
        },
        "84": {
          "rect": {
            "x": 412,
            "y": 417,
            "width": 66,
            "height": 81
          },
          "xOffset": -4,
          "yOffset": 6,
          "xAdvance": 54
        },
        "85": {
          "rect": {
            "x": 421,
            "y": 334,
            "width": 67,
            "height": 81
          },
          "xOffset": 3,
          "yOffset": 6,
          "xAdvance": 67
        },
        "86": {
          "rect": {
            "x": 480,
            "y": 417,
            "width": 73,
            "height": 81
          },
          "xOffset": -4,
          "yOffset": 6,
          "xAdvance": 60
        },
        "87": {
          "rect": {
            "x": 487,
            "y": 188,
            "width": 103,
            "height": 81
          },
          "xOffset": -4,
          "yOffset": 6,
          "xAdvance": 91
        },
        "88": {
          "rect": {
            "x": 532,
            "y": 84,
            "width": 69,
            "height": 81
          },
          "xOffset": -2,
          "yOffset": 6,
          "xAdvance": 61
        },
        "89": {
          "rect": {
            "x": 490,
            "y": 271,
            "width": 70,
            "height": 81
          },
          "xOffset": -4,
          "yOffset": 6,
          "xAdvance": 58
        },
        "90": {
          "rect": {
            "x": 555,
            "y": 354,
            "width": 62,
            "height": 81
          },
          "xOffset": -1,
          "yOffset": 6,
          "xAdvance": 54
        },
        "91": {
          "rect": {
            "x": 742,
            "y": 384,
            "width": 35,
            "height": 93
          },
          "xOffset": 2,
          "yOffset": 7,
          "xAdvance": 31
        },
        "93": {
          "rect": {
            "x": 742,
            "y": 2,
            "width": 35,
            "height": 93
          },
          "xOffset": -2,
          "yOffset": 7,
          "xAdvance": 31
        },
        "94": {
          "rect": {
            "x": 589,
            "y": 440,
            "width": 51,
            "height": 47
          },
          "xOffset": -2,
          "yOffset": 6,
          "xAdvance": 44
        },
        "95": {
          "rect": {
            "x": 91,
            "y": 485,
            "width": 64,
            "height": 23
          },
          "xOffset": -2,
          "yOffset": 71,
          "xAdvance": 55
        },
        "97": {
          "rect": {
            "x": 2,
            "y": 2,
            "width": 56,
            "height": 64
          },
          "xOffset": -2,
          "yOffset": 24,
          "xAdvance": 45
        },
        "98": {
          "rect": {
            "x": 2,
            "y": 68,
            "width": 57,
            "height": 86
          },
          "xOffset": 0,
          "yOffset": 2,
          "xAdvance": 51
        },
        "99": {
          "rect": {
            "x": 60,
            "y": 2,
            "width": 54,
            "height": 64
          },
          "xOffset": -1,
          "yOffset": 24,
          "xAdvance": 47
        },
        "100": {
          "rect": {
            "x": 2,
            "y": 156,
            "width": 63,
            "height": 86
          },
          "xOffset": -1,
          "yOffset": 2,
          "xAdvance": 54
        },
        "101": {
          "rect": {
            "x": 61,
            "y": 68,
            "width": 53,
            "height": 64
          },
          "xOffset": -1,
          "yOffset": 24,
          "xAdvance": 46
        },
        "102": {
          "rect": {
            "x": 2,
            "y": 244,
            "width": 55,
            "height": 107
          },
          "xOffset": -4,
          "yOffset": 0,
          "xAdvance": 31
        },
        "103": {
          "rect": {
            "x": 2,
            "y": 353,
            "width": 57,
            "height": 91
          },
          "xOffset": -2,
          "yOffset": 16,
          "xAdvance": 46
        },
        "104": {
          "rect": {
            "x": 59,
            "y": 244,
            "width": 62,
            "height": 86
          },
          "xOffset": 1,
          "yOffset": 2,
          "xAdvance": 55
        },
        "105": {
          "rect": {
            "x": 67,
            "y": 134,
            "width": 33,
            "height": 83
          },
          "xOffset": 1,
          "yOffset": 5,
          "xAdvance": 26
        },
        "106": {
          "rect": {
            "x": 102,
            "y": 134,
            "width": 32,
            "height": 101
          },
          "xOffset": -4,
          "yOffset": 5,
          "xAdvance": 25
        },
        "107": {
          "rect": {
            "x": 116,
            "y": 2,
            "width": 57,
            "height": 86
          },
          "xOffset": 1,
          "yOffset": 2,
          "xAdvance": 49
        },
        "108": {
          "rect": {
            "x": 61,
            "y": 332,
            "width": 33,
            "height": 86
          },
          "xOffset": 1,
          "yOffset": 2,
          "xAdvance": 26
        },
        "109": {
          "rect": {
            "x": 2,
            "y": 446,
            "width": 87,
            "height": 63
          },
          "xOffset": 1,
          "yOffset": 24,
          "xAdvance": 80
        },
        "110": {
          "rect": {
            "x": 91,
            "y": 420,
            "width": 62,
            "height": 63
          },
          "xOffset": 1,
          "yOffset": 24,
          "xAdvance": 55
        },
        "111": {
          "rect": {
            "x": 96,
            "y": 332,
            "width": 61,
            "height": 64
          },
          "xOffset": -1,
          "yOffset": 24,
          "xAdvance": 54
        },
        "112": {
          "rect": {
            "x": 123,
            "y": 237,
            "width": 58,
            "height": 83
          },
          "xOffset": 1,
          "yOffset": 24,
          "xAdvance": 53
        },
        "113": {
          "rect": {
            "x": 155,
            "y": 398,
            "width": 57,
            "height": 83
          },
          "xOffset": -1,
          "yOffset": 24,
          "xAdvance": 52
        },
        "114": {
          "rect": {
            "x": 159,
            "y": 322,
            "width": 43,
            "height": 63
          },
          "xOffset": 1,
          "yOffset": 24,
          "xAdvance": 36
        },
        "115": {
          "rect": {
            "x": 136,
            "y": 90,
            "width": 47,
            "height": 64
          },
          "xOffset": -1,
          "yOffset": 24,
          "xAdvance": 40
        },
        "116": {
          "rect": {
            "x": 136,
            "y": 156,
            "width": 45,
            "height": 72
          },
          "xOffset": -1,
          "yOffset": 16,
          "xAdvance": 35
        },
        "117": {
          "rect": {
            "x": 175,
            "y": 2,
            "width": 62,
            "height": 63
          },
          "xOffset": 0,
          "yOffset": 24,
          "xAdvance": 54
        },
        "118": {
          "rect": {
            "x": 183,
            "y": 156,
            "width": 59,
            "height": 63
          },
          "xOffset": -5,
          "yOffset": 24,
          "xAdvance": 46
        },
        "119": {
          "rect": {
            "x": 185,
            "y": 67,
            "width": 85,
            "height": 63
          },
          "xOffset": -5,
          "yOffset": 24,
          "xAdvance": 72
        },
        "120": {
          "rect": {
            "x": 239,
            "y": 2,
            "width": 56,
            "height": 63
          },
          "xOffset": -3,
          "yOffset": 24,
          "xAdvance": 46
        },
        "121": {
          "rect": {
            "x": 183,
            "y": 221,
            "width": 59,
            "height": 83
          },
          "xOffset": -5,
          "yOffset": 24,
          "xAdvance": 46
        },
        "122": {
          "rect": {
            "x": 204,
            "y": 306,
            "width": 52,
            "height": 62
          },
          "xOffset": -2,
          "yOffset": 25,
          "xAdvance": 43
        },
        "123": {
          "rect": {
            "x": 657,
            "y": 384,
            "width": 40,
            "height": 104
          },
          "xOffset": -2,
          "yOffset": 5,
          "xAdvance": 32
        },
        "124": {
          "rect": {
            "x": 662,
            "y": 2,
            "width": 23,
            "height": 95
          },
          "xOffset": 2,
          "yOffset": 7,
          "xAdvance": 24
        },
        "125": {
          "rect": {
            "x": 699,
            "y": 384,
            "width": 41,
            "height": 104
          },
          "xOffset": -2,
          "yOffset": 5,
          "xAdvance": 32
        },
        "8470": {
          "rect": {
            "x": 59,
            "y": 332,
            "width": 0,
            "height": 0
          },
          "xOffset": 0,
          "yOffset": 72,
          "xAdvance": 21
        }
      },
      "kerningDict": {}
    }
  },
  {
    "__type__": "cc.SpriteFrame",
    "content": {
      "name": "game_minigame_totalscore_backtogame",
      "texture": "75ty/AxiZM0bqDcmClfWel",
      "rect": [
        1,
        1,
        296,
        73
      ],
      "offset": [
        0,
        0
      ],
      "originalSize": [
        298,
        75
      ],
      "capInsets": [
        0,
        0,
        0,
        0
      ]
    }
  },
  [
    {
      "__type__": "cc.Prefab",
      "_name": "MiniGame4",
      "data": {
        "__id__": 1
      }
    },
    {
      "__type__": "cc.Node",
      "_name": "MiniGame4",
      "_children": [
        {
          "__id__": 2
        },
        {
          "__id__": 3
        },
        {
          "__id__": 4
        },
        {
          "__id__": 18
        },
        {
          "__id__": 35
        },
        {
          "__id__": 53
        }
      ],
      "_level": 1,
      "_components": [
        {
          "__type__": "94608N0ZWxGmJDiObfqNnTw",
          "node": {
            "__id__": 1
          },
          "itemsContainer": {
            "__id__": 22
          },
          "mainGame": {
            "__id__": 18
          },
          "gameResult": {
            "__id__": 35
          },
          "labelGr": {
            "__id__": 7
          },
          "labelMa": {
            "__id__": 10
          },
          "labelMino": {
            "__id__": 13
          },
          "labelMini": {
            "__id__": 16
          },
          "coinLabel": {
            "__id__": 44
          },
          "labelJackpot": {
            "__id__": 39
          },
          "resourceController": {
            "__id__": 54
          }
        },
        {
          "__type__": "cc.Widget",
          "node": {
            "__id__": 1
          },
          "_alignFlags": 45
        }
      ],
      "_prefab": {
        "__type__": "cc.PrefabInfo",
        "root": {
          "__id__": 1
        },
        "asset": {
          "__uuid__": "ecWWHpBI1Cl6AoXq+bba2w"
        },
        "fileId": "0dOCMX+yNP9buJpBPhIsse"
      },
      "_contentSize": {
        "__type__": "cc.Size",
        "width": 1280,
        "height": 720
      },
      "_position": {
        "__type__": "cc.Vec3",
        "x": 640,
        "y": 360
      }
    },
    {
      "__type__": "cc.Node",
      "_name": "bg-big",
      "_parent": {
        "__id__": 1
      },
      "_level": 2,
      "_components": [
        {
          "__type__": "cc.Sprite",
          "node": {
            "__id__": 2
          },
          "_sizeMode": 0
        },
        {
          "__type__": "cc.Widget",
          "node": {
            "__id__": 2
          },
          "_alignFlags": 45,
          "_originalWidth": 1280,
          "_originalHeight": 720
        }
      ],
      "_prefab": {
        "__type__": "cc.PrefabInfo",
        "root": {
          "__id__": 1
        },
        "asset": {
          "__uuid__": "ecWWHpBI1Cl6AoXq+bba2w"
        },
        "fileId": "63Ua6N0x5IgZFWsgs9Glg0"
      },
      "_contentSize": {
        "__type__": "cc.Size",
        "width": 1280,
        "height": 720
      }
    },
    {
      "__type__": "cc.Node",
      "_name": "bonus-coin-2",
      "_parent": {
        "__id__": 1
      },
      "_active": false,
      "_level": 2,
      "_components": [
        {
          "__type__": "cc.Sprite",
          "node": {
            "__id__": 3
          }
        }
      ],
      "_prefab": {
        "__type__": "cc.PrefabInfo",
        "root": {
          "__id__": 1
        },
        "asset": {
          "__uuid__": "ecWWHpBI1Cl6AoXq+bba2w"
        },
        "fileId": "99QcEUea9GJZa3jseIdPTs"
      },
      "_contentSize": {
        "__type__": "cc.Size",
        "width": 1280,
        "height": 720
      },
      "_position": {
        "__type__": "cc.Vec3",
        "y": 9
      }
    },
    {
      "__type__": "cc.Node",
      "_name": "top",
      "_parent": {
        "__id__": 1
      },
      "_children": [
        {
          "__id__": 5
        },
        {
          "__id__": 8
        },
        {
          "__id__": 11
        },
        {
          "__id__": 14
        },
        {
          "__id__": 17
        }
      ],
      "_level": 2,
      "_prefab": {
        "__type__": "cc.PrefabInfo",
        "root": {
          "__id__": 1
        },
        "asset": {
          "__uuid__": "ecWWHpBI1Cl6AoXq+bba2w"
        },
        "fileId": "e1Isyst4FBf6VThn6QpeqM"
      }
    },
    {
      "__type__": "cc.Node",
      "_name": "casino-slot-bg-grand-money",
      "_parent": {
        "__id__": 4
      },
      "_children": [
        {
          "__id__": 6
        }
      ],
      "_level": 3,
      "_components": [
        {
          "__type__": "cc.Sprite",
          "node": {
            "__id__": 5
          }
        }
      ],
      "_prefab": {
        "__type__": "cc.PrefabInfo",
        "root": {
          "__id__": 1
        },
        "asset": {
          "__uuid__": "ecWWHpBI1Cl6AoXq+bba2w"
        },
        "fileId": "4fMo45C9lFQ5ysZFMz8cws"
      },
      "_contentSize": {
        "__type__": "cc.Size",
        "width": 321,
        "height": 48
      },
      "_position": {
        "__type__": "cc.Vec3",
        "x": -279,
        "y": 300
      }
    },
    {
      "__type__": "cc.Node",
      "_name": "labelGrand",
      "_parent": {
        "__id__": 5
      },
      "_level": 4,
      "_components": [
        {
          "__id__": 7
        }
      ],
      "_prefab": {
        "__type__": "cc.PrefabInfo",
        "root": {
          "__id__": 1
        },
        "asset": {
          "__uuid__": "ecWWHpBI1Cl6AoXq+bba2w"
        },
        "fileId": "43DuTYihBH4LRCdypkOtHM"
      },
      "_contentSize": {
        "__type__": "cc.Size",
        "width": 96.8,
        "height": 16
      },
      "_position": {
        "__type__": "cc.Vec3",
        "x": 34,
        "y": 4
      }
    },
    {
      "__type__": "cc.Label",
      "node": {
        "__id__": 6
      },
      "_useOriginalSize": false,
      "_string": "1000000",
      "_N$string": "1000000",
      "_fontSize": 24,
      "_N$file": {
        "__uuid__": "5a8qsGXPZB7a3N/Hg1rpTQ"
      },
      "_isSystemFontUsed": false,
      "_N$horizontalAlign": 1,
      "_N$verticalAlign": 1
    },
    {
      "__type__": "cc.Node",
      "_name": "casino-slot-bg-major-money",
      "_parent": {
        "__id__": 4
      },
      "_children": [
        {
          "__id__": 9
        }
      ],
      "_level": 3,
      "_components": [
        {
          "__type__": "cc.Sprite",
          "node": {
            "__id__": 8
          }
        }
      ],
      "_prefab": {
        "__type__": "cc.PrefabInfo",
        "root": {
          "__id__": 1
        },
        "asset": {
          "__uuid__": "ecWWHpBI1Cl6AoXq+bba2w"
        },
        "fileId": "91kaYo/RlMHa0pmNLkhuzL"
      },
      "_contentSize": {
        "__type__": "cc.Size",
        "width": 321,
        "height": 48
      },
      "_position": {
        "__type__": "cc.Vec3",
        "x": 280,
        "y": 300
      }
    },
    {
      "__type__": "cc.Node",
      "_name": "labelMajor",
      "_parent": {
        "__id__": 8
      },
      "_level": 4,
      "_components": [
        {
          "__id__": 10
        }
      ],
      "_prefab": {
        "__type__": "cc.PrefabInfo",
        "root": {
          "__id__": 1
        },
        "asset": {
          "__uuid__": "ecWWHpBI1Cl6AoXq+bba2w"
        },
        "fileId": "383unO7b5ORLBoEw5Rd3P+"
      },
      "_contentSize": {
        "__type__": "cc.Size",
        "width": 15.2,
        "height": 16
      },
      "_position": {
        "__type__": "cc.Vec3",
        "x": -56,
        "y": 4
      }
    },
    {
      "__type__": "cc.Label",
      "node": {
        "__id__": 9
      },
      "_useOriginalSize": false,
      "_string": "0",
      "_N$string": "0",
      "_fontSize": 24,
      "_N$file": {
        "__uuid__": "5a8qsGXPZB7a3N/Hg1rpTQ"
      },
      "_isSystemFontUsed": false,
      "_N$horizontalAlign": 1,
      "_N$verticalAlign": 1
    },
    {
      "__type__": "cc.Node",
      "_name": "casino-slot-bg-mini-money",
      "_parent": {
        "__id__": 4
      },
      "_children": [
        {
          "__id__": 12
        }
      ],
      "_level": 3,
      "_components": [
        {
          "__type__": "cc.Sprite",
          "node": {
            "__id__": 11
          }
        }
      ],
      "_prefab": {
        "__type__": "cc.PrefabInfo",
        "root": {
          "__id__": 1
        },
        "asset": {
          "__uuid__": "ecWWHpBI1Cl6AoXq+bba2w"
        },
        "fileId": "3dLuQP28ZIAoSiBnlBhwub"
      },
      "_contentSize": {
        "__type__": "cc.Size",
        "width": 321,
        "height": 44
      },
      "_position": {
        "__type__": "cc.Vec3",
        "x": 290,
        "y": 240
      }
    },
    {
      "__type__": "cc.Node",
      "_name": "labelMini",
      "_parent": {
        "__id__": 11
      },
      "_level": 4,
      "_components": [
        {
          "__id__": 13
        }
      ],
      "_prefab": {
        "__type__": "cc.PrefabInfo",
        "root": {
          "__id__": 1
        },
        "asset": {
          "__uuid__": "ecWWHpBI1Cl6AoXq+bba2w"
        },
        "fileId": "18s6l0Gb5BHaA/P9KEnSvk"
      },
      "_contentSize": {
        "__type__": "cc.Size",
        "width": 15.2,
        "height": 16
      },
      "_position": {
        "__type__": "cc.Vec3",
        "x": -59,
        "y": 4
      }
    },
    {
      "__type__": "cc.Label",
      "node": {
        "__id__": 12
      },
      "_useOriginalSize": false,
      "_string": "0",
      "_N$string": "0",
      "_fontSize": 24,
      "_N$file": {
        "__uuid__": "5a8qsGXPZB7a3N/Hg1rpTQ"
      },
      "_isSystemFontUsed": false,
      "_N$horizontalAlign": 1,
      "_N$verticalAlign": 1
    },
    {
      "__type__": "cc.Node",
      "_name": "casino-slot-bg-minor-money",
      "_parent": {
        "__id__": 4
      },
      "_children": [
        {
          "__id__": 15
        }
      ],
      "_level": 3,
      "_components": [
        {
          "__type__": "cc.Sprite",
          "node": {
            "__id__": 14
          }
        }
      ],
      "_prefab": {
        "__type__": "cc.PrefabInfo",
        "root": {
          "__id__": 1
        },
        "asset": {
          "__uuid__": "ecWWHpBI1Cl6AoXq+bba2w"
        },
        "fileId": "9cfvOCQ6hPiLQJEZXt2ZyR"
      },
      "_contentSize": {
        "__type__": "cc.Size",
        "width": 321,
        "height": 44
      },
      "_position": {
        "__type__": "cc.Vec3",
        "x": -288,
        "y": 240
      }
    },
    {
      "__type__": "cc.Node",
      "_name": "labelMinor",
      "_parent": {
        "__id__": 14
      },
      "_level": 4,
      "_components": [
        {
          "__id__": 16
        }
      ],
      "_prefab": {
        "__type__": "cc.PrefabInfo",
        "root": {
          "__id__": 1
        },
        "asset": {
          "__uuid__": "ecWWHpBI1Cl6AoXq+bba2w"
        },
        "fileId": "96FJaDm7RPm4JMxb/VdqaF"
      },
      "_contentSize": {
        "__type__": "cc.Size",
        "width": 15.2,
        "height": 16
      },
      "_position": {
        "__type__": "cc.Vec3",
        "x": 58,
        "y": 4
      }
    },
    {
      "__type__": "cc.Label",
      "node": {
        "__id__": 15
      },
      "_useOriginalSize": false,
      "_string": "0",
      "_N$string": "0",
      "_fontSize": 24,
      "_N$file": {
        "__uuid__": "5a8qsGXPZB7a3N/Hg1rpTQ"
      },
      "_isSystemFontUsed": false,
      "_N$horizontalAlign": 1,
      "_N$verticalAlign": 1
    },
    {
      "__type__": "cc.Node",
      "_name": "casino-slot-bg-coin-colect-money",
      "_parent": {
        "__id__": 4
      },
      "_level": 3,
      "_components": [
        {
          "__type__": "cc.Sprite",
          "node": {
            "__id__": 17
          }
        }
      ],
      "_prefab": {
        "__type__": "cc.PrefabInfo",
        "root": {
          "__id__": 1
        },
        "asset": {
          "__uuid__": "ecWWHpBI1Cl6AoXq+bba2w"
        },
        "fileId": "cbuiPcQX5LpJgMe1cIxsLZ"
      },
      "_contentSize": {
        "__type__": "cc.Size",
        "width": 207,
        "height": 100
      },
      "_position": {
        "__type__": "cc.Vec3",
        "y": 272
      }
    },
    {
      "__type__": "cc.Node",
      "_name": "game",
      "_parent": {
        "__id__": 1
      },
      "_children": [
        {
          "__id__": 19
        },
        {
          "__id__": 20
        },
        {
          "__id__": 22
        }
      ],
      "_level": 2,
      "_prefab": {
        "__type__": "cc.PrefabInfo",
        "root": {
          "__id__": 1
        },
        "asset": {
          "__uuid__": "ecWWHpBI1Cl6AoXq+bba2w"
        },
        "fileId": "a2EC+H9KBDpbJ2dmAHqQnh"
      },
      "_contentSize": {
        "__type__": "cc.Size",
        "width": 1116,
        "height": 531
      },
      "_position": {
        "__type__": "cc.Vec3",
        "y": -78
      }
    },
    {
      "__type__": "cc.Node",
      "_name": "casino-slot-coin-bg-bonus-coin",
      "_parent": {
        "__id__": 18
      },
      "_level": 3,
      "_components": [
        {
          "__type__": "cc.Sprite",
          "node": {
            "__id__": 19
          }
        }
      ],
      "_prefab": {
        "__type__": "cc.PrefabInfo",
        "root": {
          "__id__": 1
        },
        "asset": {
          "__uuid__": "ecWWHpBI1Cl6AoXq+bba2w"
        },
        "fileId": "515CyO0s9CEIY4xBp0wQap"
      },
      "_contentSize": {
        "__type__": "cc.Size",
        "width": 1116,
        "height": 531
      }
    },
    {
      "__type__": "cc.Node",
      "_name": "title",
      "_parent": {
        "__id__": 18
      },
      "_children": [
        {
          "__id__": 21
        }
      ],
      "_level": 3,
      "_prefab": {
        "__type__": "cc.PrefabInfo",
        "root": {
          "__id__": 1
        },
        "asset": {
          "__uuid__": "ecWWHpBI1Cl6AoXq+bba2w"
        },
        "fileId": "a6sdI0GlhCTor+G0ShoE1B"
      },
      "_contentSize": {
        "__type__": "cc.Size",
        "width": 662,
        "height": 89
      },
      "_position": {
        "__type__": "cc.Vec3",
        "x": 3,
        "y": 222
      }
    },
    {
      "__type__": "cc.Node",
      "_name": "casino-slot-bg-txt-bonus-coin",
      "_parent": {
        "__id__": 20
      },
      "_level": 4,
      "_components": [
        {
          "__type__": "cc.Sprite",
          "node": {
            "__id__": 21
          }
        }
      ],
      "_prefab": {
        "__type__": "cc.PrefabInfo",
        "root": {
          "__id__": 1
        },
        "asset": {
          "__uuid__": "ecWWHpBI1Cl6AoXq+bba2w"
        },
        "fileId": "e7DuoKlbhJFIrYIp9+Zdwh"
      },
      "_contentSize": {
        "__type__": "cc.Size",
        "width": 662,
        "height": 89
      }
    },
    {
      "__type__": "cc.Node",
      "_name": "itemsContainer",
      "_parent": {
        "__id__": 18
      },
      "_children": [
        {
          "__id__": 23
        },
        {
          "__id__": 24
        },
        {
          "__id__": 25
        },
        {
          "__id__": 26
        },
        {
          "__id__": 27
        },
        {
          "__id__": 28
        },
        {
          "__id__": 29
        },
        {
          "__id__": 30
        },
        {
          "__id__": 31
        },
        {
          "__id__": 32
        },
        {
          "__id__": 33
        },
        {
          "__id__": 34
        }
      ],
      "_level": 3,
      "_prefab": {
        "__type__": "cc.PrefabInfo",
        "root": {
          "__id__": 1
        },
        "asset": {
          "__uuid__": "ecWWHpBI1Cl6AoXq+bba2w"
        },
        "fileId": "15AdbwXYROZLTbFz8JCa7l"
      },
      "_contentSize": {
        "__type__": "cc.Size",
        "width": 1029,
        "height": 417
      },
      "_anchorPoint": {
        "__type__": "cc.Vec2"
      },
      "_position": {
        "__type__": "cc.Vec3",
        "x": -510,
        "y": -230
      }
    },
    {
      "__type__": "cc.Node",
      "_name": "0",
      "_parent": {
        "__id__": 22
      },
      "_children": [
        {
          "__type__": "cc.Node",
          "_name": "casino-slot-coin-normal",
          "_parent": {
            "__id__": 23
          },
          "_active": false,
          "_level": 5,
          "_prefab": {
            "__type__": "cc.PrefabInfo",
            "root": {
              "__id__": 1
            },
            "asset": {
              "__uuid__": "ecWWHpBI1Cl6AoXq+bba2w"
            },
            "fileId": "0cL8Xa24JGYID0KaIjghK5"
          },
          "_contentSize": {
            "__type__": "cc.Size",
            "width": 148,
            "height": 148
          }
        }
      ],
      "_level": 4,
      "_prefab": {
        "__type__": "cc.PrefabInfo",
        "root": {
          "__id__": 1
        },
        "asset": {
          "__uuid__": "ecWWHpBI1Cl6AoXq+bba2w"
        },
        "fileId": "27toYfOMZPU6c4ztCmZdi1"
      },
      "_contentSize": {
        "__type__": "cc.Size",
        "width": 148,
        "height": 148
      },
      "_position": {
        "__type__": "cc.Vec3",
        "x": 83,
        "y": 133
      }
    },
    {
      "__type__": "cc.Node",
      "_name": "01",
      "_parent": {
        "__id__": 22
      },
      "_children": [
        {
          "__type__": "cc.Node",
          "_name": "casino-slot-coin-normal",
          "_parent": {
            "__id__": 24
          },
          "_active": false,
          "_level": 5,
          "_prefab": {
            "__type__": "cc.PrefabInfo",
            "root": {
              "__id__": 1
            },
            "asset": {
              "__uuid__": "ecWWHpBI1Cl6AoXq+bba2w"
            },
            "fileId": "0bVU/+SARA4Y/DV3rVgCqP"
          },
          "_contentSize": {
            "__type__": "cc.Size",
            "width": 148,
            "height": 148
          }
        }
      ],
      "_level": 4,
      "_prefab": {
        "__type__": "cc.PrefabInfo",
        "root": {
          "__id__": 1
        },
        "asset": {
          "__uuid__": "ecWWHpBI1Cl6AoXq+bba2w"
        },
        "fileId": "a1Mg2QVF5MhJo3nsFm4pFE"
      },
      "_contentSize": {
        "__type__": "cc.Size",
        "width": 148,
        "height": 148
      },
      "_position": {
        "__type__": "cc.Vec3",
        "x": 255,
        "y": 133
      }
    },
    {
      "__type__": "cc.Node",
      "_name": "02",
      "_parent": {
        "__id__": 22
      },
      "_children": [
        {
          "__type__": "cc.Node",
          "_name": "casino-slot-coin-normal",
          "_parent": {
            "__id__": 25
          },
          "_active": false,
          "_level": 5,
          "_prefab": {
            "__type__": "cc.PrefabInfo",
            "root": {
              "__id__": 1
            },
            "asset": {
              "__uuid__": "ecWWHpBI1Cl6AoXq+bba2w"
            },
            "fileId": "482VJnIzlEfKYxAYI/LHMY"
          },
          "_contentSize": {
            "__type__": "cc.Size",
            "width": 148,
            "height": 148
          }
        }
      ],
      "_level": 4,
      "_prefab": {
        "__type__": "cc.PrefabInfo",
        "root": {
          "__id__": 1
        },
        "asset": {
          "__uuid__": "ecWWHpBI1Cl6AoXq+bba2w"
        },
        "fileId": "90sA8YcJNDfbA03cVK7Eyh"
      },
      "_contentSize": {
        "__type__": "cc.Size",
        "width": 148,
        "height": 148
      },
      "_position": {
        "__type__": "cc.Vec3",
        "x": 421,
        "y": 133
      }
    },
    {
      "__type__": "cc.Node",
      "_name": "03",
      "_parent": {
        "__id__": 22
      },
      "_children": [
        {
          "__type__": "cc.Node",
          "_name": "casino-slot-coin-normal",
          "_parent": {
            "__id__": 26
          },
          "_active": false,
          "_level": 5,
          "_prefab": {
            "__type__": "cc.PrefabInfo",
            "root": {
              "__id__": 1
            },
            "asset": {
              "__uuid__": "ecWWHpBI1Cl6AoXq+bba2w"
            },
            "fileId": "cdVzwfq71LbKZqDLurIz0x"
          },
          "_contentSize": {
            "__type__": "cc.Size",
            "width": 148,
            "height": 148
          }
        }
      ],
      "_level": 4,
      "_prefab": {
        "__type__": "cc.PrefabInfo",
        "root": {
          "__id__": 1
        },
        "asset": {
          "__uuid__": "ecWWHpBI1Cl6AoXq+bba2w"
        },
        "fileId": "62LP1wVOtM5qVTp9LtQWyP"
      },
      "_contentSize": {
        "__type__": "cc.Size",
        "width": 148,
        "height": 148
      },
      "_position": {
        "__type__": "cc.Vec3",
        "x": 592,
        "y": 133
      }
    },
    {
      "__type__": "cc.Node",
      "_name": "04",
      "_parent": {
        "__id__": 22
      },
      "_children": [
        {
          "__type__": "cc.Node",
          "_name": "casino-slot-coin-normal",
          "_parent": {
            "__id__": 27
          },
          "_active": false,
          "_level": 5,
          "_prefab": {
            "__type__": "cc.PrefabInfo",
            "root": {
              "__id__": 1
            },
            "asset": {
              "__uuid__": "ecWWHpBI1Cl6AoXq+bba2w"
            },
            "fileId": "9b6EAz6SFGG5IS4nbgx7U+"
          },
          "_contentSize": {
            "__type__": "cc.Size",
            "width": 148,
            "height": 148
          }
        }
      ],
      "_level": 4,
      "_prefab": {
        "__type__": "cc.PrefabInfo",
        "root": {
          "__id__": 1
        },
        "asset": {
          "__uuid__": "ecWWHpBI1Cl6AoXq+bba2w"
        },
        "fileId": "0fNW/UyaBC+6qmU69YRH+H"
      },
      "_contentSize": {
        "__type__": "cc.Size",
        "width": 148,
        "height": 148
      },
      "_position": {
        "__type__": "cc.Vec3",
        "x": 764.4,
        "y": 133
      }
    },
    {
      "__type__": "cc.Node",
      "_name": "05",
      "_parent": {
        "__id__": 22
      },
      "_children": [
        {
          "__type__": "cc.Node",
          "_name": "casino-slot-coin-normal",
          "_parent": {
            "__id__": 28
          },
          "_active": false,
          "_level": 5,
          "_prefab": {
            "__type__": "cc.PrefabInfo",
            "root": {
              "__id__": 1
            },
            "asset": {
              "__uuid__": "ecWWHpBI1Cl6AoXq+bba2w"
            },
            "fileId": "09nKq381tIra4j7M7u9V5P"
          },
          "_contentSize": {
            "__type__": "cc.Size",
            "width": 148,
            "height": 148
          }
        }
      ],
      "_level": 4,
      "_prefab": {
        "__type__": "cc.PrefabInfo",
        "root": {
          "__id__": 1
        },
        "asset": {
          "__uuid__": "ecWWHpBI1Cl6AoXq+bba2w"
        },
        "fileId": "3b3AajXHpF8KX79MJqVjNm"
      },
      "_contentSize": {
        "__type__": "cc.Size",
        "width": 148,
        "height": 148
      },
      "_position": {
        "__type__": "cc.Vec3",
        "x": 932.6,
        "y": 132
      }
    },
    {
      "__type__": "cc.Node",
      "_name": "06",
      "_parent": {
        "__id__": 22
      },
      "_children": [
        {
          "__type__": "cc.Node",
          "_name": "casino-slot-coin-normal",
          "_parent": {
            "__id__": 29
          },
          "_active": false,
          "_level": 5,
          "_prefab": {
            "__type__": "cc.PrefabInfo",
            "root": {
              "__id__": 1
            },
            "asset": {
              "__uuid__": "ecWWHpBI1Cl6AoXq+bba2w"
            },
            "fileId": "58woJ/lT5ALrUs3+zNdAxQ"
          },
          "_contentSize": {
            "__type__": "cc.Size",
            "width": 148,
            "height": 148
          }
        }
      ],
      "_level": 4,
      "_prefab": {
        "__type__": "cc.PrefabInfo",
        "root": {
          "__id__": 1
        },
        "asset": {
          "__uuid__": "ecWWHpBI1Cl6AoXq+bba2w"
        },
        "fileId": "26C40aHZ9ItZIe7A7mz1ri"
      },
      "_contentSize": {
        "__type__": "cc.Size",
        "width": 148,
        "height": 148
      },
      "_position": {
        "__type__": "cc.Vec3",
        "x": 81.9,
        "y": 290
      }
    },
    {
      "__type__": "cc.Node",
      "_name": "07",
      "_parent": {
        "__id__": 22
      },
      "_children": [
        {
          "__type__": "cc.Node",
          "_name": "casino-slot-coin-normal",
          "_parent": {
            "__id__": 30
          },
          "_active": false,
          "_level": 5,
          "_prefab": {
            "__type__": "cc.PrefabInfo",
            "root": {
              "__id__": 1
            },
            "asset": {
              "__uuid__": "ecWWHpBI1Cl6AoXq+bba2w"
            },
            "fileId": "55K2OYJKlOqpk8X8eHpl+s"
          },
          "_contentSize": {
            "__type__": "cc.Size",
            "width": 148,
            "height": 148
          }
        }
      ],
      "_level": 4,
      "_prefab": {
        "__type__": "cc.PrefabInfo",
        "root": {
          "__id__": 1
        },
        "asset": {
          "__uuid__": "ecWWHpBI1Cl6AoXq+bba2w"
        },
        "fileId": "d2vscHkdRFnLi1m1HTWq7u"
      },
      "_contentSize": {
        "__type__": "cc.Size",
        "width": 148,
        "height": 148
      },
      "_position": {
        "__type__": "cc.Vec3",
        "x": 252.3,
        "y": 291.4
      }
    },
    {
      "__type__": "cc.Node",
      "_name": "08",
      "_parent": {
        "__id__": 22
      },
      "_children": [
        {
          "__type__": "cc.Node",
          "_name": "casino-slot-coin-normal",
          "_parent": {
            "__id__": 31
          },
          "_active": false,
          "_level": 5,
          "_prefab": {
            "__type__": "cc.PrefabInfo",
            "root": {
              "__id__": 1
            },
            "asset": {
              "__uuid__": "ecWWHpBI1Cl6AoXq+bba2w"
            },
            "fileId": "4cIHV9tpNN7JawLlcL1PBx"
          },
          "_contentSize": {
            "__type__": "cc.Size",
            "width": 148,
            "height": 148
          }
        }
      ],
      "_level": 4,
      "_prefab": {
        "__type__": "cc.PrefabInfo",
        "root": {
          "__id__": 1
        },
        "asset": {
          "__uuid__": "ecWWHpBI1Cl6AoXq+bba2w"
        },
        "fileId": "d8tPzgr6dItaYmj+U/IK4q"
      },
      "_contentSize": {
        "__type__": "cc.Size",
        "width": 148,
        "height": 148
      },
      "_position": {
        "__type__": "cc.Vec3",
        "x": 422.1,
        "y": 294
      }
    },
    {
      "__type__": "cc.Node",
      "_name": "09",
      "_parent": {
        "__id__": 22
      },
      "_children": [
        {
          "__type__": "cc.Node",
          "_name": "casino-slot-coin-normal",
          "_parent": {
            "__id__": 32
          },
          "_active": false,
          "_level": 5,
          "_prefab": {
            "__type__": "cc.PrefabInfo",
            "root": {
              "__id__": 1
            },
            "asset": {
              "__uuid__": "ecWWHpBI1Cl6AoXq+bba2w"
            },
            "fileId": "d8RdYPZgpKB6uWoyziUPKy"
          },
          "_contentSize": {
            "__type__": "cc.Size",
            "width": 148,
            "height": 148
          }
        }
      ],
      "_level": 4,
      "_prefab": {
        "__type__": "cc.PrefabInfo",
        "root": {
          "__id__": 1
        },
        "asset": {
          "__uuid__": "ecWWHpBI1Cl6AoXq+bba2w"
        },
        "fileId": "2e0/li96BDL4qwnfcE71Nz"
      },
      "_contentSize": {
        "__type__": "cc.Size",
        "width": 148,
        "height": 148
      },
      "_position": {
        "__type__": "cc.Vec3",
        "x": 593.1,
        "y": 293
      }
    },
    {
      "__type__": "cc.Node",
      "_name": "10",
      "_parent": {
        "__id__": 22
      },
      "_children": [
        {
          "__type__": "cc.Node",
          "_name": "casino-slot-coin-normal",
          "_parent": {
            "__id__": 33
          },
          "_active": false,
          "_level": 5,
          "_prefab": {
            "__type__": "cc.PrefabInfo",
            "root": {
              "__id__": 1
            },
            "asset": {
              "__uuid__": "ecWWHpBI1Cl6AoXq+bba2w"
            },
            "fileId": "6fZeCkJSlCQoelxjaqJkEV"
          },
          "_contentSize": {
            "__type__": "cc.Size",
            "width": 148,
            "height": 148
          }
        }
      ],
      "_level": 4,
      "_prefab": {
        "__type__": "cc.PrefabInfo",
        "root": {
          "__id__": 1
        },
        "asset": {
          "__uuid__": "ecWWHpBI1Cl6AoXq+bba2w"
        },
        "fileId": "f1FTDmAU1Iradw3cs5YoUL"
      },
      "_contentSize": {
        "__type__": "cc.Size",
        "width": 148,
        "height": 148
      },
      "_position": {
        "__type__": "cc.Vec3",
        "x": 764.4,
        "y": 293
      }
    },
    {
      "__type__": "cc.Node",
      "_name": "11",
      "_parent": {
        "__id__": 22
      },
      "_children": [
        {
          "__type__": "cc.Node",
          "_name": "casino-slot-coin-normal",
          "_parent": {
            "__id__": 34
          },
          "_active": false,
          "_level": 5,
          "_prefab": {
            "__type__": "cc.PrefabInfo",
            "root": {
              "__id__": 1
            },
            "asset": {
              "__uuid__": "ecWWHpBI1Cl6AoXq+bba2w"
            },
            "fileId": "aeNMPFQf5GOroufZ+gh3uI"
          },
          "_contentSize": {
            "__type__": "cc.Size",
            "width": 148,
            "height": 148
          }
        }
      ],
      "_level": 4,
      "_prefab": {
        "__type__": "cc.PrefabInfo",
        "root": {
          "__id__": 1
        },
        "asset": {
          "__uuid__": "ecWWHpBI1Cl6AoXq+bba2w"
        },
        "fileId": "75GxFAzAFMxbPPGOh+IRnc"
      },
      "_contentSize": {
        "__type__": "cc.Size",
        "width": 148,
        "height": 148
      },
      "_position": {
        "__type__": "cc.Vec3",
        "x": 934.2,
        "y": 291.6
      }
    },
    {
      "__type__": "cc.Node",
      "_name": "result-table",
      "_parent": {
        "__id__": 1
      },
      "_children": [
        {
          "__id__": 36
        },
        {
          "__id__": 37
        },
        {
          "__id__": 41
        },
        {
          "__id__": 45
        },
        {
          "__id__": 47
        },
        {
          "__id__": 49
        },
        {
          "__id__": 50
        }
      ],
      "_active": false,
      "_level": 2,
      "_prefab": {
        "__type__": "cc.PrefabInfo",
        "root": {
          "__id__": 1
        },
        "asset": {
          "__uuid__": "ecWWHpBI1Cl6AoXq+bba2w"
        },
        "fileId": "de1TpBC7xJKZNPWo4ysnAA"
      }
    },
    {
      "__type__": "cc.Node",
      "_name": "bg-big-result",
      "_parent": {
        "__id__": 35
      },
      "_level": 3,
      "_components": [
        {
          "__type__": "cc.Sprite",
          "node": {
            "__id__": 36
          }
        },
        {
          "__type__": "cc.Button",
          "node": {
            "__id__": 36
          },
          "_N$interactable": false
        }
      ],
      "_prefab": {
        "__type__": "cc.PrefabInfo",
        "root": {
          "__id__": 1
        },
        "asset": {
          "__uuid__": "ecWWHpBI1Cl6AoXq+bba2w"
        },
        "fileId": "c4uWz/wNVG3qVJEhZffkmN"
      },
      "_contentSize": {
        "__type__": "cc.Size",
        "width": 1173,
        "height": 751
      }
    },
    {
      "__type__": "cc.Node",
      "_name": "top",
      "_parent": {
        "__id__": 35
      },
      "_children": [
        {
          "__id__": 38
        },
        {
          "__id__": 40
        }
      ],
      "_level": 3,
      "_prefab": {
        "__type__": "cc.PrefabInfo",
        "root": {
          "__id__": 1
        },
        "asset": {
          "__uuid__": "ecWWHpBI1Cl6AoXq+bba2w"
        },
        "fileId": "66etxlscVBTo1+FjppYqjH"
      },
      "_position": {
        "__type__": "cc.Vec3",
        "y": 196
      }
    },
    {
      "__type__": "cc.Node",
      "_name": "typeJPLable",
      "_parent": {
        "__id__": 37
      },
      "_level": 4,
      "_components": [
        {
          "__id__": 39
        }
      ],
      "_prefab": {
        "__type__": "cc.PrefabInfo",
        "root": {
          "__id__": 1
        },
        "asset": {
          "__uuid__": "ecWWHpBI1Cl6AoXq+bba2w"
        },
        "fileId": "321N2XezBLjYM3oT2oWiHp"
      },
      "_contentSize": {
        "__type__": "cc.Size",
        "width": 598,
        "height": 40
      },
      "_position": {
        "__type__": "cc.Vec3",
        "y": 26.4
      }
    },
    {
      "__type__": "cc.Label",
      "node": {
        "__id__": 38
      },
      "_useOriginalSize": false,
      "_string": "Grand Jackpot",
      "_N$string": "Grand Jackpot",
      "_fontSize": 90,
      "_N$file": {
        "__uuid__": "dbApQIXIZFHoF3C7Gf6NxV"
      },
      "_isSystemFontUsed": false,
      "_N$horizontalAlign": 1,
      "_N$verticalAlign": 1
    },
    {
      "__type__": "cc.Node",
      "_name": "typeJPLable copy",
      "_parent": {
        "__id__": 37
      },
      "_level": 4,
      "_components": [
        {
          "__type__": "cc.Label",
          "node": {
            "__id__": 40
          },
          "_useOriginalSize": false,
          "_string": "Grand Jackpot",
          "_N$string": "Grand Jackpot",
          "_fontSize": 90,
          "_N$file": {
            "__uuid__": "dbApQIXIZFHoF3C7Gf6NxV"
          },
          "_isSystemFontUsed": false,
          "_N$horizontalAlign": 1,
          "_N$verticalAlign": 1
        }
      ],
      "_prefab": {
        "__type__": "cc.PrefabInfo",
        "root": {
          "__id__": 1
        },
        "asset": {
          "__uuid__": "ecWWHpBI1Cl6AoXq+bba2w"
        },
        "fileId": "063uC2KmxP4b7MBtxo//SI"
      },
      "_contentSize": {
        "__type__": "cc.Size",
        "width": 598,
        "height": 40
      },
      "_position": {
        "__type__": "cc.Vec3",
        "y": 26.4
      }
    },
    {
      "__type__": "cc.Node",
      "_name": "bg-money-win",
      "_parent": {
        "__id__": 35
      },
      "_children": [
        {
          "__id__": 42
        },
        {
          "__id__": 43
        }
      ],
      "_level": 3,
      "_prefab": {
        "__type__": "cc.PrefabInfo",
        "root": {
          "__id__": 1
        },
        "asset": {
          "__uuid__": "ecWWHpBI1Cl6AoXq+bba2w"
        },
        "fileId": "4chJ2PNy5HWJRxXk4EOqbz"
      },
      "_contentSize": {
        "__type__": "cc.Size",
        "width": 959,
        "height": 178
      }
    },
    {
      "__type__": "cc.Node",
      "_name": "Casino-bg-congrat-bg-money-win",
      "_parent": {
        "__id__": 41
      },
      "_level": 4,
      "_components": [
        {
          "__type__": "cc.Sprite",
          "node": {
            "__id__": 42
          }
        }
      ],
      "_prefab": {
        "__type__": "cc.PrefabInfo",
        "root": {
          "__id__": 1
        },
        "asset": {
          "__uuid__": "ecWWHpBI1Cl6AoXq+bba2w"
        },
        "fileId": "14Qn3/w3dNc4FvOLf6VvbK"
      },
      "_contentSize": {
        "__type__": "cc.Size",
        "width": 959,
        "height": 178
      }
    },
    {
      "__type__": "cc.Node",
      "_name": "coinLabel",
      "_parent": {
        "__id__": 41
      },
      "_level": 4,
      "_components": [
        {
          "__id__": 44
        }
      ],
      "_prefab": {
        "__type__": "cc.PrefabInfo",
        "root": {
          "__id__": 1
        },
        "asset": {
          "__uuid__": "ecWWHpBI1Cl6AoXq+bba2w"
        },
        "fileId": "efPrJkFAhPxYx92hHu1IYv"
      },
      "_contentSize": {
        "__type__": "cc.Size",
        "width": 662,
        "height": 80
      },
      "_position": {
        "__type__": "cc.Vec3",
        "y": 20
      }
    },
    {
      "__type__": "cc.Label",
      "node": {
        "__id__": 43
      },
      "_useOriginalSize": false,
      "_string": "1,234,567,890",
      "_N$string": "1,234,567,890",
      "_fontSize": 100,
      "_N$file": {
        "__uuid__": "19t+Nvk2VEbpHwGOqyOUL6"
      },
      "_isSystemFontUsed": false,
      "_N$horizontalAlign": 1,
      "_N$verticalAlign": 1,
      "_N$overflow": 2
    },
    {
      "__type__": "cc.Node",
      "_name": "txt-coin",
      "_parent": {
        "__id__": 35
      },
      "_children": [
        {
          "__id__": 46
        }
      ],
      "_level": 3,
      "_prefab": {
        "__type__": "cc.PrefabInfo",
        "root": {
          "__id__": 1
        },
        "asset": {
          "__uuid__": "ecWWHpBI1Cl6AoXq+bba2w"
        },
        "fileId": "8dIcbOcd5LOoJPZ2szqowU"
      },
      "_contentSize": {
        "__type__": "cc.Size",
        "width": 141,
        "height": 45
      },
      "_position": {
        "__type__": "cc.Vec3",
        "x": 2,
        "y": -121
      }
    },
    {
      "__type__": "cc.Node",
      "_name": "Casino-bg-congrat-txt-coin",
      "_parent": {
        "__id__": 45
      },
      "_level": 4,
      "_components": [
        {
          "__type__": "cc.Sprite",
          "node": {
            "__id__": 46
          }
        }
      ],
      "_prefab": {
        "__type__": "cc.PrefabInfo",
        "root": {
          "__id__": 1
        },
        "asset": {
          "__uuid__": "ecWWHpBI1Cl6AoXq+bba2w"
        },
        "fileId": "35kex4lZJAYams2yPlzVia"
      },
      "_contentSize": {
        "__type__": "cc.Size",
        "width": 141,
        "height": 45
      }
    },
    {
      "__type__": "cc.Node",
      "_name": "txt-youwin",
      "_parent": {
        "__id__": 35
      },
      "_children": [
        {
          "__id__": 48
        }
      ],
      "_level": 3,
      "_prefab": {
        "__type__": "cc.PrefabInfo",
        "root": {
          "__id__": 1
        },
        "asset": {
          "__uuid__": "ecWWHpBI1Cl6AoXq+bba2w"
        },
        "fileId": "8aBIL0SPpKHLz1VUDznYUs"
      },
      "_contentSize": {
        "__type__": "cc.Size",
        "width": 230,
        "height": 44
      },
      "_position": {
        "__type__": "cc.Vec3",
        "y": 110
      }
    },
    {
      "__type__": "cc.Node",
      "_name": "Casino-bg-congrat-txt-youwin",
      "_parent": {
        "__id__": 47
      },
      "_level": 4,
      "_components": [
        {
          "__type__": "cc.Sprite",
          "node": {
            "__id__": 48
          }
        }
      ],
      "_prefab": {
        "__type__": "cc.PrefabInfo",
        "root": {
          "__id__": 1
        },
        "asset": {
          "__uuid__": "ecWWHpBI1Cl6AoXq+bba2w"
        },
        "fileId": "63Bu8DMDdNCadh9sW4GuUP"
      },
      "_contentSize": {
        "__type__": "cc.Size",
        "width": 230,
        "height": 44
      }
    },
    {
      "__type__": "cc.Node",
      "_name": "const-backToGame",
      "_parent": {
        "__id__": 35
      },
      "_level": 3,
      "_components": [
        {
          "__type__": "cc.Sprite",
          "node": {
            "__id__": 49
          },
          "_spriteFrame": {
            "__uuid__": "e9YSqke7RKR6DWAr4h0ERl"
          }
        },
        {
          "__type__": "cc.Button",
          "node": {
            "__id__": 49
          },
          "zoomScale": 0.9,
          "clickEvents": [
            {
              "__type__": "cc.ClickEvent",
              "target": {
                "__id__": 1
              },
              "_componentId": "94608N0ZWxGmJDiObfqNnTw",
              "handler": "backToSlot"
            }
          ],
          "_N$transition": 3,
          "transition": 3
        }
      ],
      "_prefab": {
        "__type__": "cc.PrefabInfo",
        "root": {
          "__id__": 1
        },
        "asset": {
          "__uuid__": "ecWWHpBI1Cl6AoXq+bba2w"
        },
        "fileId": "b3+hxXXYNG47nPSVh0si9e"
      },
      "_contentSize": {
        "__type__": "cc.Size",
        "width": 296,
        "height": 73
      },
      "_position": {
        "__type__": "cc.Vec3",
        "y": -204
      }
    },
    {
      "__type__": "cc.Node",
      "_name": "bottom",
      "_parent": {
        "__id__": 35
      },
      "_children": [
        {
          "__id__": 51
        }
      ],
      "_level": 3,
      "_prefab": {
        "__type__": "cc.PrefabInfo",
        "root": {
          "__id__": 1
        },
        "asset": {
          "__uuid__": "ecWWHpBI1Cl6AoXq+bba2w"
        },
        "fileId": "bahcgr3ZBPXormLUluWPYc"
      }
    },
    {
      "__type__": "cc.Node",
      "_name": "const-game_minigame_totalscore_iconshare",
      "_parent": {
        "__id__": 50
      },
      "_children": [
        {
          "__id__": 52
        }
      ],
      "_level": 4,
      "_components": [
        {
          "__type__": "cc.Sprite",
          "node": {
            "__id__": 51
          },
          "_spriteFrame": {
            "__uuid__": "48aI31qb9F5IQ49aCJb0VK"
          }
        }
      ],
      "_prefab": {
        "__type__": "cc.PrefabInfo",
        "root": {
          "__id__": 1
        },
        "asset": {
          "__uuid__": "ecWWHpBI1Cl6AoXq+bba2w"
        },
        "fileId": "9dNid55I5A9KwDlGtySQEP"
      },
      "_contentSize": {
        "__type__": "cc.Size",
        "width": 29,
        "height": 28
      },
      "_position": {
        "__type__": "cc.Vec3",
        "x": -144,
        "y": -293
      }
    },
    {
      "__type__": "cc.Node",
      "_name": "const-share",
      "_parent": {
        "__id__": 51
      },
      "_level": 5,
      "_components": [
        {
          "__type__": "cc.Label",
          "node": {
            "__id__": 52
          },
          "_useOriginalSize": false,
          "_string": "Share with facebook",
          "_N$string": "Share with facebook",
          "_fontSize": 35,
          "_N$file": {
            "__uuid__": "16ghaQKjJOfLDvTizedZAV"
          },
          "_isSystemFontUsed": false,
          "_N$horizontalAlign": 1,
          "_N$verticalAlign": 1
        }
      ],
      "_prefab": {
        "__type__": "cc.PrefabInfo",
        "root": {
          "__id__": 1
        },
        "asset": {
          "__uuid__": "ecWWHpBI1Cl6AoXq+bba2w"
        },
        "fileId": "6de4X8vm5M7J+28UbDf9Qr"
      },
      "_contentSize": {
        "__type__": "cc.Size",
        "width": 285.25,
        "height": 35
      },
      "_position": {
        "__type__": "cc.Vec3",
        "x": 171,
        "y": 6
      }
    },
    {
      "__type__": "cc.Node",
      "_name": "ResourceController",
      "_parent": {
        "__id__": 1
      },
      "_level": 2,
      "_components": [
        {
          "__id__": 54
        }
      ],
      "_prefab": {
        "__type__": "cc.PrefabInfo",
        "root": {
          "__id__": 1
        },
        "asset": {
          "__uuid__": "ecWWHpBI1Cl6AoXq+bba2w"
        },
        "fileId": "676NT14HpB67bRfyeqqHib"
      }
    },
    {
      "__type__": "3030cAzQURD1ZwN5t1Kyglx",
      "node": {
        "__id__": 53
      },
      "listImage": [
        {
          "__type__": "ImageItem",
          "image": {
            "__id__": 2
          },
          "customName": "bg-big.jpg",
          "folderPath": "img"
        },
        {
          "__type__": "ImageItem",
          "image": {
            "__id__": 5
          },
          "folderPath": "img"
        },
        {
          "__type__": "ImageItem",
          "image": {
            "__id__": 8
          },
          "folderPath": "img"
        },
        {
          "__type__": "ImageItem",
          "image": {
            "__id__": 11
          },
          "folderPath": "img"
        },
        {
          "__type__": "ImageItem",
          "image": {
            "__id__": 14
          },
          "folderPath": "img"
        },
        {
          "__type__": "ImageItem",
          "image": {
            "__id__": 17
          },
          "folderPath": "img"
        },
        {
          "__type__": "ImageItem",
          "image": {
            "__id__": 21
          }
        },
        {
          "__type__": "ImageItem",
          "image": {
            "__id__": 36
          }
        },
        {
          "__type__": "ImageItem",
          "image": {
            "__id__": 42
          }
        },
        {
          "__type__": "ImageItem",
          "image": {
            "__id__": 46
          }
        },
        {
          "__type__": "ImageItem",
          "image": {
            "__id__": 48
          }
        },
        {
          "__type__": "ImageItem",
          "image": {
            "__id__": 19
          }
        }
      ]
    }
  ]
]